README.rst
setup.py
loud/__init__.py
loud/loud.py
loud.egg-info/PKG-INFO
loud.egg-info/SOURCES.txt
loud.egg-info/dependency_links.txt
loud.egg-info/entry_points.txt
loud.egg-info/requires.txt
loud.egg-info/top_level.txt