Metadata-Version: 1.1
Name: loud
Version: 0.1.2
Summary: Nose plugin for sound notification
Home-page: http://github.com/kusut/loud
Author: kusut
Author-email: kusut@dahsy.at
License: MIT
Keywords: nose plugin testing audio
Platform: UNKNOWN
Classifier: Intended Audience :: Developers
Classifier: Programming Language :: Python
Classifier: Programming Language :: Python :: 2.6
Classifier: Programming Language :: Python :: 2.7
Classifier: Programming Language :: Python :: Implementation :: CPython
Classifier: Topic :: Software Development :: Testing
Classifier: License :: OSI Approved :: MIT License
